Metadata-Version: 2.1
Name: nonebot2-plugin-RealESRGAN
Version: 0.2.2
Summary: 一个基于nonebot2机器人的对图像进行超分辨率重建插件
Home-page: https://github.com/ppxxxg22/nonebot_plugin_RealESRGAN
Author: ppxxxg22
Author-email: liujiaxin011121@gmail.com
License: BSD 3-Clause
Platform: UNKNOWN
Classifier: License :: OSI Approved :: BSD License
Classifier: Programming Language :: Python
Classifier: Programming Language :: Python :: 3
Classifier: Programming Language :: Python :: 3.7
Classifier: Programming Language :: Python :: Implementation :: CPython
Classifier: Programming Language :: Python :: Implementation :: PyPy
Requires-Python: >=3.7.0
